zope.contentprovider-6.1-py3.12-nspkg.pth
zope/contentprovider/__init__.py
zope/contentprovider/configure.zcml
zope/contentprovider/interfaces.py
zope/contentprovider/provider.py
zope/contentprovider/tales.py
zope/contentprovider/tests.py
zope_contentprovider-6.1.dist-info/licenses/LICENSE.txt
zope_contentprovider-6.1.dist-info/METADATA
zope_contentprovider-6.1.dist-info/WHEEL
zope_contentprovider-6.1.dist-info/namespace_packages.txt
zope_contentprovider-6.1.dist-info/top_level.txt
zope_contentprovider-6.1.dist-info/RECORD
